advdask/__init__.py
advdask/core.py
advdask-0.1.0.dist-info/LICENSE
advdask-0.1.0.dist-info/METADATA
advdask-0.1.0.dist-info/WHEEL
advdask-0.1.0.dist-info/top_level.txt
advdask-0.1.0.dist-info/RECORD
