Metadata-Version: 2.2
Name: advdask
Version: 0.1.0
Summary: An advanced extension of the Dask library.
Home-page: https://github.com/Sumedh1599/advdask
Author: Sumedh Patil
Author-email: your-email@example.com
Classifier: Programming Language :: Python :: 3
Classifier: License :: OSI Approved :: MIT License
Classifier: Operating System :: OS Independent
Requires-Python: >=3.6
License-File: LICENSE
Requires-Dist: dask>=2023.0.0
Requires-Dist: numpy>=1.15.0
Dynamic: author
Dynamic: author-email
Dynamic: classifier
Dynamic: description
Dynamic: description-content-type
Dynamic: home-page
Dynamic: requires-dist
Dynamic: requires-python
Dynamic: summary
